MANIFEST.in
setup.py
peptagram/__init__.py
peptagram/fasta.py
peptagram/mascot.py
peptagram/maxquant.py
peptagram/morpheus.py
peptagram/mzml.py
peptagram/parse.py
peptagram/peptidemass.py
peptagram/proteins.py
peptagram/tpp.py
peptagram/xtandem.py
peptagram.egg-info/PKG-INFO
peptagram.egg-info/SOURCES.txt
peptagram.egg-info/dependency_links.txt
peptagram.egg-info/requires.txt
peptagram.egg-info/top_level.txt
peptagram/templates/comparison/index.html
peptagram/templates/comparison/main.js
peptagram/templates/js/canvaswidget.js
peptagram/templates/js/datacontroller.js
peptagram/templates/js/jquery-2.0.3.js
peptagram/templates/js/mass.js
peptagram/templates/js/peptidelist.js
peptagram/templates/js/proteinlist.js
peptagram/templates/js/spectrumwidget.js
peptagram/templates/js/util.js
peptagram/templates/overview/index.html
peptagram/templates/overview/main.js