Metadata-Version: 1.0
Name: peptagram
Version: 0.2.2
Summary: python scripts to generate javascript visualization for proteomics data
Home-page: http://boscoh.github.io/peptagram
Author: Bosco Ho
Author-email: boscoh@gmail.com
License: BSD
Platform: UNKNOWN
